LICENSE
MANIFEST.in
README.rst
setup.cfg
setup.py
one_tap_sign_in/__init__.py
one_tap_sign_in/admin.py
one_tap_sign_in/apps.py
one_tap_sign_in/config.py
one_tap_sign_in/models.py
one_tap_sign_in/tests.py
one_tap_sign_in/urls.py
one_tap_sign_in/utils.py
one_tap_sign_in/views.py
one_tap_sign_in.egg-info/PKG-INFO
one_tap_sign_in.egg-info/SOURCES.txt
one_tap_sign_in.egg-info/dependency_links.txt
one_tap_sign_in.egg-info/requires.txt
one_tap_sign_in.egg-info/top_level.txt
one_tap_sign_in/migrations/__init__.py