Metadata-Version: 2.1
Name: one_tap_sign_in
Version: 0.3
Summary: A Django app to use services of phone.email.
Home-page: https://www.phone.email/
Author: Uday sk
Author-email: burluudaysantoshkumar3@gmail.com
License: BSD-3-Clause
Classifier: Environment :: Web Environment
Classifier: Framework :: Django
Classifier: Intended Audience :: Developers
Classifier: License :: OSI Approved :: BSD License
Classifier: Programming Language :: Python :: 3 :: Only
License-File: LICENSE
Requires-Dist: requests
